spriteutilkangkang/__init__.py
spriteutilkangkang/spriteutil.py
spriteutilkangkang-1.0.0.dist-info/LICENSE
spriteutilkangkang-1.0.0.dist-info/METADATA
spriteutilkangkang-1.0.0.dist-info/WHEEL
spriteutilkangkang-1.0.0.dist-info/top_level.txt
spriteutilkangkang-1.0.0.dist-info/RECORD
