Metadata-Version: 2.1
Name: spriteutilkangkang
Version: 1.0.0
Summary: UNKNOWN
Home-page: https://github.com/haphongpk12/Sprite-Sheet
Author: Khang TRAN
Author-email: haphong12@gmail.com
Maintainer: Khang TRAN
License: MIT
Platform: UNKNOWN
Classifier: Programming Language :: Python :: 3
Classifier: License :: OSI Approved :: MIT License
Classifier: Operating System :: OS Independent
Requires-Python: >=3.7
